{
	"credit": "Made with Blockbench",
	"parent": "block/block",
	"textures": {
		"particle": "losgallysprops:block/traffic_lights/modern/modern_traffic_light"
	},
	"elements": [
		{
			"name": "glass",
			"from": [3, 8, 1.875],
			"to": [13, 18, 1.875],
			"faces": {
				"north": {"uv": [0, 0, 16, 16], "texture": "#red"},
				"east": {"uv": [0, 0, 0, 16], "texture": "#missing"},
				"west": {"uv": [0, 0, 0, 16], "texture": "#missing"},
				"up": {"uv": [0, 0, 10, 0], "texture": "#missing"},
				"down": {"uv": [0, 0, 10, 0], "texture": "#missing"}
			}
		},
		{
			"name": "glass",
			"from": [3, -2, 1.875],
			"to": [13, 8, 1.875],
			"faces": {
				"north": {"uv": [0, 0, 16, 16], "texture": "#green"},
				"east": {"uv": [0, 0, 0, 16], "texture": "#missing"},
				"west": {"uv": [0, 0, 0, 16], "texture": "#missing"},
				"up": {"uv": [0, 0, 10, 0], "texture": "#missing"},
				"down": {"uv": [0, 0, 10, 0], "texture": "#missing"}
			}
		}
	]
}